<?xml version="1.0"?>
<!DOCTYPE hibernate-mapping PUBLIC "-//Hibernate/Hibernate Mapping DTD 3.0//EN"
"http://www.hibernate.org/dtd/hibernate-mapping-3.0.dtd">
<!-- Generated Sep 3, 2018 7:40:07 AM by Hibernate Tools 4.3.1 -->
<hibernate-mapping>
    <class name="pojoClass.VipInfo" table="vip_info" catalog="topazvip" optimistic-lock="version">
        <id name="id" type="java.lang.Integer">
            <column name="id" />
            <generator class="identity" />
        </id>
        <property name="fullname" type="string">
            <column name="Fullname" length="30" not-null="true" />
        </property>
        <property name="idNumber" type="string">
            <column name="Id_Number" length="10" not-null="true" />
        </property>
        <property name="image1" type="blob">
            <column name="Image1" not-null="true" />
        </property>
        <property name="image2" type="blob">
            <column name="Image2" not-null="true" />
        </property>
        <property name="image3" type="blob">
            <column name="Image3" not-null="true" />
        </property>
        <property name="image4" type="blob">
            <column name="Image4" not-null="true" />
        </property>
        <property name="image5" type="blob">
            <column name="Image5" not-null="true" />
        </property>
    </class>
</hibernate-mapping>
